aiomygas/__init__.py
aiomygas/__main__.py
aiomygas/_version.py
aiomygas/api.py
aiomygas/auth.py
aiomygas/cli.py
aiomygas/const.py
aiomygas/device_info.py
aiomygas/devices.json
aiomygas/exceptions.py
aiomygas/py.typed
aiomygas/queries/__init__.py
aiomygas/queries/accounts.py
aiomygas/queries/base.py
aiomygas/queries/charges.py
aiomygas/queries/client.py
aiomygas/queries/els_info.py
aiomygas/queries/indication_send.py
aiomygas/queries/lspu_info.py
aiomygas/queries/payments.py
aiomygas/queries/receipt.py
aiomygas/queries/signin.py
aiomygas-2.3.0.dist-info/LICENSE
aiomygas-2.3.0.dist-info/METADATA
aiomygas-2.3.0.dist-info/WHEEL
aiomygas-2.3.0.dist-info/entry_points.txt
aiomygas-2.3.0.dist-info/top_level.txt
aiomygas-2.3.0.dist-info/RECORD
