Metadata-Version: 2.1
Name: aiomygas
Version: 2.3.0
Summary: Asynchronous Python API For My Gas
Author: LizardSystems
License: MIT License
Project-URL: Home, https://github.com/lizardsystems/aiomygas
Project-URL: Repository, https://github.com/lizardsystems/aiomygas
Project-URL: Documentation, https://github.com/lizardsystems/aiomygas
Project-URL: Bug Tracker, https://github.com/lizardsystems/aiomygas/issues
Project-URL: Changelog, https://github.com/lizardsystems/aiomygas/blob/master/CHANGELOG.md
Keywords: energy,gas
Platform: any
Classifier: Development Status :: 5 - Production/Stable
Classifier: License :: OSI Approved :: MIT License
Classifier: Intended Audience :: Developers
Classifier: Operating System :: OS Independent
Classifier: Programming Language :: Python
Classifier: Programming Language :: Python :: 3
Classifier: Programming Language :: Python :: 3.9
Classifier: Programming Language :: Python :: 3.10
Classifier: Programming Language :: Python :: 3.11
Classifier: Programming Language :: Python :: 3.12
Classifier: Programming Language :: Python :: 3 :: Only
Classifier: Typing :: Typed
Requires-Python: >=3.9.0
License-File: LICENSE
Requires-Dist: aiohttp
